{
  "generated": "2026-05-11T05:00:34.885228Z",
  "period": {
    "start": "2025-05-11",
    "end": "2026-05-11"
  },
  "total": 0,
  "hits_by_day": [],
  "by_lang": {},
  "by_section": {},
  "browsers": [
    {
      "name": "Safari",
      "id": "Safari",
      "count": 973
    },
    {
      "name": "Chrome",
      "id": "Chrome",
      "count": 589
    },
    {
      "name": "Firefox",
      "id": "Firefox",
      "count": 45
    },
    {
      "name": "Desconegut",
      "id": "Desconegut",
      "count": 8
    }
  ],
  "systems": [
    {
      "name": "iOS",
      "id": "iOS",
      "count": 908
    },
    {
      "name": "Android",
      "id": "Android",
      "count": 345
    },
    {
      "name": "macOS",
      "id": "macOS",
      "count": 184
    },
    {
      "name": "Windows",
      "id": "Windows",
      "count": 129
    },
    {
      "name": "Linux",
      "id": "Linux",
      "count": 49
    }
  ],
  "sizes": [
    {
      "name": "phone",
      "id": "phone",
      "count": 1239
    },
    {
      "name": "desktop",
      "id": "desktop",
      "count": 211
    },
    {
      "name": "desktophd",
      "id": "desktophd",
      "count": 133
    },
    {
      "name": "tablet",
      "id": "tablet",
      "count": 32
    }
  ],
  "locations": [
    {
      "name": "Spain",
      "id": "ES",
      "count": 1484
    },
    {
      "name": "United States",
      "id": "US",
      "count": 45
    },
    {
      "name": "France",
      "id": "FR",
      "count": 12
    },
    {
      "name": "Netherlands",
      "id": "NL",
      "count": 10
    },
    {
      "name": "United Kingdom",
      "id": "GB",
      "count": 9
    },
    {
      "name": "Australia",
      "id": "AU",
      "count": 6
    },
    {
      "name": "Greece",
      "id": "GR",
      "count": 6
    },
    {
      "name": "Italy",
      "id": "IT",
      "count": 6
    },
    {
      "name": "Ireland",
      "id": "IE",
      "count": 5
    },
    {
      "name": "Israel",
      "id": "IL",
      "count": 5
    }
  ]
}