{
  "generated": "2026-06-05T12:13:11.360901Z",
  "period": {
    "start": "2025-06-05",
    "end": "2026-06-05"
  },
  "total": 0,
  "hits_by_day": [],
  "by_lang": {},
  "by_section": {},
  "browsers": [
    {
      "name": "Safari",
      "id": "Safari",
      "count": 1563
    },
    {
      "name": "Chrome",
      "id": "Chrome",
      "count": 942
    },
    {
      "name": "Firefox",
      "id": "Firefox",
      "count": 69
    },
    {
      "name": "Desconegut",
      "id": "Desconegut",
      "count": 17
    }
  ],
  "systems": [
    {
      "name": "iOS",
      "id": "iOS",
      "count": 1463
    },
    {
      "name": "Android",
      "id": "Android",
      "count": 575
    },
    {
      "name": "macOS",
      "id": "macOS",
      "count": 253
    },
    {
      "name": "Windows",
      "id": "Windows",
      "count": 231
    },
    {
      "name": "Linux",
      "id": "Linux",
      "count": 69
    }
  ],
  "sizes": [
    {
      "name": "phone",
      "id": "phone",
      "count": 2026
    },
    {
      "name": "desktop",
      "id": "desktop",
      "count": 377
    },
    {
      "name": "desktophd",
      "id": "desktophd",
      "count": 147
    },
    {
      "name": "tablet",
      "id": "tablet",
      "count": 41
    }
  ],
  "locations": [
    {
      "name": "Spain",
      "id": "ES",
      "count": 2353
    },
    {
      "name": "United States",
      "id": "US",
      "count": 64
    },
    {
      "name": "United Kingdom",
      "id": "GB",
      "count": 24
    },
    {
      "name": "Netherlands",
      "id": "NL",
      "count": 19
    },
    {
      "name": "France",
      "id": "FR",
      "count": 17
    },
    {
      "name": "Germany",
      "id": "DE",
      "count": 14
    },
    {
      "name": "Italy",
      "id": "IT",
      "count": 11
    },
    {
      "name": "Ireland",
      "id": "IE",
      "count": 10
    },
    {
      "name": "Greece",
      "id": "GR",
      "count": 9
    },
    {
      "name": "Australia",
      "id": "AU",
      "count": 6
    }
  ]
}